mcp_git_analyzer/__init__.py
mcp_git_analyzer/config.py
mcp_git_analyzer/server.py
mcp_git_analyzer/db/__init__.py
mcp_git_analyzer/db/schema.py
mcp_git_analyzer/parsers/__init__.py
mcp_git_analyzer/parsers/algorithm_extractor.py
mcp_git_analyzer/parsers/base_parser.py
mcp_git_analyzer/parsers/c_parser.py
mcp_git_analyzer/parsers/cpp_parser.py
mcp_git_analyzer/parsers/csharp_parser.py
mcp_git_analyzer/parsers/go_parser.py
mcp_git_analyzer/parsers/java_parser.py
mcp_git_analyzer/parsers/javascript_parser.py
mcp_git_analyzer/parsers/language_detector.py
mcp_git_analyzer/parsers/python_parser.py
mcp_git_analyzer/parsers/rust_parser.py
mcp_git_analyzer/parsers/similarity.py
mcp_git_analyzer/parsers/typescript_parser.py
mcp_git_analyzer/tools/__init__.py
mcp_git_analyzer/tools/algorithm_tools.py
mcp_git_analyzer/tools/analysis_tools.py
mcp_git_analyzer/tools/git_tools.py
mcp_git_analyzer/tools/report_tools.py
mcp_git_analyzer/tools/search_tools.py
mcp_git_analyzer-0.1.7.dist-info/METADATA
mcp_git_analyzer-0.1.7.dist-info/WHEEL
mcp_git_analyzer-0.1.7.dist-info/entry_points.txt
mcp_git_analyzer-0.1.7.dist-info/licenses/LICENSE
mcp_git_analyzer-0.1.7.dist-info/RECORD
