Metadata-Version: 2.4
Name: mcp-git-analyzer
Version: 0.1.7
Summary: MCP server for analyzing Git repositories - extracts code structure, patterns, and documentation
Project-URL: Homepage, https://github.com/crlotwhite/mcp-git-analyzer
Project-URL: Repository, https://github.com/crlotwhite/mcp-git-analyzer
Project-URL: Issues, https://github.com/crlotwhite/mcp-git-analyzer/issues
Author: crlotwhite
License-Expression: MIT
License-File: LICENSE
Keywords: analyzer,code-analysis,git,mcp,model-context-protocol
Classifier: Development Status :: 3 - Alpha
Classifier: Intended Audience :: Developers
Classifier: License :: OSI Approved :: MIT License
Classifier: Programming Language :: Python :: 3
Classifier: Programming Language :: Python :: 3.10
Classifier: Programming Language :: Python :: 3.11
Classifier: Programming Language :: Python :: 3.12
Requires-Python: >=3.10
Requires-Dist: gitpython>=3.1.0
Requires-Dist: mcp[cli]>=1.2.0
Requires-Dist: ruff>=0.14.7
Requires-Dist: tools>=1.0.15
Requires-Dist: tree-sitter-c-sharp>=0.23.0
Requires-Dist: tree-sitter-c>=0.23.0
Requires-Dist: tree-sitter-cpp>=0.23.0
Requires-Dist: tree-sitter-go>=0.23.0
Requires-Dist: tree-sitter-java>=0.23.0
Requires-Dist: tree-sitter-javascript>=0.23.0
Requires-Dist: tree-sitter-python>=0.23.0
Requires-Dist: tree-sitter-rust>=0.23.0
Requires-Dist: tree-sitter-typescript>=0.23.0
Requires-Dist: tree-sitter>=0.24.0
Provides-Extra: ann
Requires-Dist: faiss-cpu>=1.7.4; extra == 'ann'
Requires-Dist: numpy>=1.24.0; extra == 'ann'
Requires-Dist: scikit-learn>=1.3.0; extra == 'ann'
Provides-Extra: dev
Requires-Dist: pytest-cov>=4.0.0; extra == 'dev'
Requires-Dist: pytest>=8.0.0; extra == 'dev'
